lintalong/__init__.py
lintalong/cli.py
lintalong/lint_along.py
lintalong/no_changed_files_exception.py
lintalong/song.py
lint_along-0.0.2.dist-info/LICENSE
lint_along-0.0.2.dist-info/METADATA
lint_along-0.0.2.dist-info/WHEEL
lint_along-0.0.2.dist-info/entry_points.txt
lint_along-0.0.2.dist-info/top_level.txt
lint_along-0.0.2.dist-info/RECORD
