Metadata-Version: 2.1
Name: lint-along
Version: 0.0.2
Summary: lint-along
Home-page: https://github.com/fowbi/lint-along
Author: fowbi
Author-email: dev@magier.com
License: The MIT License (MIT)
